sportdata/__init__.py
sportdata/info.py
sportdata-0.1.0.dist-info/METADATA
sportdata-0.1.0.dist-info/WHEEL
sportdata-0.1.0.dist-info/licenses/LICENSE
sportdata-0.1.0.dist-info/RECORD
