Metadata-Version: 2.4
Name: sportdata
Version: 0.1.0
Summary: sport data tools
License-File: LICENSE
Author: Ku-Alex-Bo
Author-email: ku.alex.bo@gmail.com
Requires-Python: >=3.12
Classifier: Programming Language :: Python :: 3
Classifier: Programming Language :: Python :: 3.12
Classifier: Programming Language :: Python :: 3.13
Classifier: Programming Language :: Python :: 3.14
